Workbook

Sheet Simulateur multi-scénarios
A1: Simulateur d'épargne — 3 scénarios
A2: Modifie les cellules en gras dans la colonne C. Tout le reste se recalcule automatiquement.
A4: Versement mensuel (€) | C4: 250
A5: Durée (années) | C5: 20
A6: Capital de départ (€) | C6: 1000
A8: Scénario | B8: Rendement annuel estimé | C8: Capital final estimé | D8: Total versé | E8: Intérêts générés
A9: Prudent | B9: 0.03 | C9: =$C$6*(1+$B9/12)^($C$5*12) + $C$4*(((1+$B9/12)^($C$5*12)-1)/($B9/12))*(1+$B9/12) | D9: =$C$4*$C$5*12+$C$6 | E9: =C9-D9
A10: Médian (ETF monde) | B10: 0.06 | C10: =$C$6*(1+$B10/12)^($C$5*12) + $C$4*(((1+$B10/12)^($C$5*12)-1)/($B10/12))*(1+$B10/12) | D10: =$C$4*$C$5*12+$C$6 | E10: =C10-D10
A11: Optimiste | B11: 0.09 | C11: =$C$6*(1+$B11/12)^($C$5*12) + $C$4*(((1+$B11/12)^($C$5*12)-1)/($B11/12))*(1+$B11/12) | D11: =$C$4*$C$5*12+$C$6 | E11: =C11-D11

Sheet Comparateur courtiers
A1: Comparateur de frais réels sur 20 ans
A2: Renseigne les frais de ton courtier pour voir leur impact réel sur ton capital final.
A4: Courtier | B4: Frais par ordre (€) | C4: Ordres / an | D4: Frais annuels | E4: Frais cumulés sur 20 ans | F4: Coût en % du capital final
A5: Bolero (KBC) | B5: 2.5 | C5: 12 | D5: =B5*C5 | E5: =D5*20 | F5: =E5/'Simulateur multi-scénarios'!$C$10
A6: Keytrade Bank | B6: 2.45 | C6: 12 | D6: =B6*C6 | E6: =D6*20 | F6: =E6/'Simulateur multi-scénarios'!$C$10
A7: MeDirect | B7: 0 | C7: 12 | D7: =B7*C7 | E7: =D7*20 | F7: =E7/'Simulateur multi-scénarios'!$C$10
A8: DEGIRO | B8: 1 | C8: 12 | D8: =B8*C8 | E8: =D8*20 | F8: =E8/'Simulateur multi-scénarios'!$C$10
A9: Saxo Bank | B9: 3 | C9: 12 | D9: =B9*C9 | E9: =D9*20 | F9: =E9/'Simulateur multi-scénarios'!$C$10
A10: Ton courtier | B10: 0 | C10: 12 | D10: =B10*C10 | E10: =D10*20 | F10: =E10/'Simulateur multi-scénarios'!$C$10

Sheet Taxe plus-values 2026
A1: Estimation de la taxe sur les plus-values (réforme 2026)
A2: Estimation indicative — vérifie toujours les règles en vigueur.
A4: Plus-value réalisée sur l'année (€) | C4: 3500
A5: Exonération annuelle applicable (€) | C5: 10000
A6: Taux d'imposition | C6: 0.1
A8: Base imposable | C8: =MAX(0, C4-C5)
A9: Impôt estimé | C9: =C8*C6
A10: Plus-value nette après impôt | C10: =C4-C9

Sheet Checklist 1er compte-titres
A1: Checklist : ouvrir ton premier compte-titres
A2: Coche chaque étape (colonne B) au fur et à mesure.
A4: Étape | B4: Fait ?
A5: Définir mon objectif d'épargne (durée, montant cible) | B5: ☐
A6: Choisir mon profil de risque (voir le quiz du site) | B6: ☐
A7: Comparer 2-3 courtiers (frais, fiscalité belge automatique) | B7: ☐
A8: Préparer ma carte d'identité électronique + lecteur de carte / app bancaire | B8: ☐
A9: Ouvrir le compte-titres en ligne chez le courtier choisi | B9: ☐
A10: Faire mon premier virement (montant que je suis prêt à investir) | B10: ☐
A11: Choisir mon premier ETF (monde, diversifié, frais bas) | B11: ☐
A12: Passer mon premier ordre d'achat | B12: ☐
A13: Mettre en place un virement automatique mensuel | B13: ☐
A14: Noter la date de ma prochaine revue de portefeuille (dans 6 mois) | B14: ☐

Sheet Suivi portefeuille
A1: Suivi de portefeuille
A2: Ajoute une ligne à chaque versement ou achat.
A4: Date | B4: Ligne (ETF / action) | C4: Montant investi (€) | D4: Valeur actuelle (€) | E4: Plus/moins-value (€) | F4: Performance
E5: =D5-C5 | F5: =IF(C5=0,"",E5/C5)
E6: =D6-C6 | F6: =IF(C6=0,"",E6/C6)
E7: =D7-C7 | F7: =IF(C7=0,"",E7/C7)
E8: =D8-C8 | F8: =IF(C8=0,"",E8/C8)
E9: =D9-C9 | F9: =IF(C9=0,"",E9/C9)
E10: =D10-C10 | F10: =IF(C10=0,"",E10/C10)
E11: =D11-C11 | F11: =IF(C11=0,"",E11/C11)
E12: =D12-C12 | F12: =IF(C12=0,"",E12/C12)
E13: =D13-C13 | F13: =IF(C13=0,"",E13/C13)
E14: =D14-C14 | F14: =IF(C14=0,"",E14/C14)
E15: =D15-C15 | F15: =IF(C15=0,"",E15/C15)
E16: =D16-C16 | F16: =IF(C16=0,"",E16/C16)
... E29: =D29-C29 | F29: =IF(C29=0,"",E29/C29)
A31: TOTAL | C31: =SUM(C5:C29) | D31: =SUM(D5:D29) | E31: =D31-C31 | F31: =IF(C31=0,"",E31/C31)

Sheet VIP — Stress-test krach
A1: 👑 — Stress-test : impact d'un krach sur ton capital
A2: Simule une chute des marchés à une année donnée et compare avec un scénario sans krach.
A4: Versement mensuel (€) | C4: 250
A5: Durée totale (années) | C5: 20
A6: Capital de départ (€) | C6: 1000
A7: Rendement annuel hors krach | C7: 0.06
A8: Année du krach | C8: 10
A9: Ampleur du krach | C9: -0.35
A10: Rendement de reprise post-krach | C10: 0.06
A13: Année | B13: Capital sans krach | C13: Capital avec krach | D13: Écart
A14: 1 | B14: =$C$6*(1+$C$7/12)^(A14*12) + $C$4*(((1+$C$7/12)^(A14*12)-1)/($C$7/12))*(1+$C$7/12) | C14: =IF(A14<$C$9, B14, ($C$6*(1+$C$7/12)^($C$9*12) + $C$4*(((1+$C$7/12)^($C$9*12)-1)/($C$7/12))*(1+$C$7/12)) * (1+$C$8) * (1+$C$10/12)^((A14-$C$9)*12) + $C$4*(((1+$C$10/12)^((A14-$C$9)*12)-1)/($C$10/12))*(1+$C$10/12)) | D14: =C14-B14
A15: 2 | B15: =$C$6*(1+$C$7/12)^(A15*12) + $C$4*(((1+$C$7/12)^(A15*12)-1)/($C$7/12))*(1+$C$7/12) | C15: =IF(A15<$C$9, B15, ($C$6*(1+$C$7/12)^($C$9*12) + $C$4*(((1+$C$7/12)^($C$9*12)-1)/($C$7/12))*(1+$C$7/12)) * (1+$C$8) * (1+$C$10/12)^((A15-$C$9)*12) + $C$4*(((1+$C$10/12)^((A15-$C$9)*12)-1)/($C$10/12))*(1+$C$10/12)) | D15: =C15-B15
A16: 3 | B16: =$C$6*(1+$C$7/12)^(A16*12) + $C$4*(((1+$C$7/12)^(A16*12)-1)/($C$7/12))*(1+$C$7/12) | C16: =IF(A16<$C$9, B16, ($C$6*(1+$C$7/12)^($C$9*12) + $C$4*(((1+$C$7/12)^($C$9*12)-1)/($C$7/12))*(1+$C$7/12)) * (1+$C$8) * (1+$C$10/12)^((A16-$C$9)*12) + $C$4*(((1+$C$10/12)^((A16-$C$9)*12)-1)/($C$10/12))*(1+$C$10/12)) | D16: =C16-B16
A17: 4 | B17: =$C$6*(1+$C$7/12)^(A17*12) + $C$4*(((1+$C$7/12)^(A17*12)-1)/($C$7/12))*(1+$C$7/12) | C17: =IF(A17<$C$9, B17, ($C$6*(1+$C$7/12)^($C$9*12) + $C$4*(((1+$C$7/12)^($C$9*12)-1)/($C$7/12))*(1+$C$7/12)) * (1+$C$8) * (1+$C$10/12)^((A17-$C$9)*12) + $C$4*(((1+$C$10/12)^((A17-$C$9)*12)-1)/($C$10/12))*(1+$C$10/12)) | D17: =C17-B17
A18: 5 | B18: =$C$6*(1+$C$7/12)^(A18*12) + $C$4*(((1+$C$7/12)^(A18*12)-1)/($C$7/12))*(1+$C$7/12) | C18: =IF(A18<$C$9, B18, ($C$6*(1+$C$7/12)^($C$9*12) + $C$4*(((1+$C$7/12)^($C$9*12)-1)/($C$7/12))*(1+$C$7/12)) * (1+$C$8) * (1+$C$10/12)^((A18-$C$9)*12) + $C$4*(((1+$C$10/12)^((A18-$C$9)*12)-1)/($C$10/12))*(1+$C$10/12)) | D18: =C18-B18
A19: 6 | B19: =$C$6*(1+$C$7/12)^(A19*12) + $C$4*(((1+$C$7/12)^(A19*12)-1)/($C$7/12))*(1+$C$7/12) | C19: =IF(A19<$C$9, B19, ($C$6*(1+$C$7/12)^($C$9*12) + $C$4*(((1+$C$7/12)^($C$9*12)-1)/($C$7/12))*(1+$C$7/12)) * (1+$C$8) * (1+$C$10/12)^((A19-$C$9)*12) + $C$4*(((1+$C$10/12)^((A19-$C$9)*12)-1)/($C$10/12))*(1+$C$10/12)) | D19: =C19-B19
A20: 7 | B20: =$C$6*(1+$C$7/12)^(A20*12) + $C$4*(((1+$C$7/12)^(A20*12)-1)/($C$7/12))*(1+$C$7/12) | C20: =IF(A20<$C$9, B20, ($C$6*(1+$C$7/12)^($C$9*12) + $C$4*(((1+$C$7/12)^($C$9*12)-1)/($C$7/12))*(1+$C$7/12)) * (1+$C$8) * (1+$C$10/12)^((A20-$C$9)*12) + $C$4*(((1+$C$10/12)^((A20-$C$9)*12)-1)/($C$10/12))*(1+$C$10/12)) | D20: =C20-B20
A21: 8 | B21: =$C$6*(1+$C$7/12)^(A21*12) + $C$4*(((1+$C$7/12)^(A21*12)-1)/($C$7/12))*(1+$C$7/12) | C21: =IF(A21<$C$9, B21, ($C$6*(1+$C$7/12)^($C$9*12) + $C$4*(((1+$C$7/12)^($C$9*12)-1)/($C$7/12))*(1+$C$7/12)) * (1+$C$8) * (1+$C$10/12)^((A21-$C$9)*12) + $C$4*(((1+$C$10/12)^((A21-$C$9)*12)-1)/($C$10/12))*(1+$C$10/12)) | D21: =C21-B21
A22: 9 | B22: =$C$6*(1+$C$7/12)^(A22*12) + $C$4*(((1+$C$7/12)^(A22*12)-1)/($C$7/12))*(1+$C$7/12) | C22: =IF(A22<$C$9, B22, ($C$6*(1+$C$7/12)^($C$9*12) + $C$4*(((1+$C$7/12)^($C$9*12)-1)/($C$7/12))*(1+$C$7/12)) * (1+$C$8) * (1+$C$10/12)^((A22-$C$9)*12) + $C$4*(((1+$C$10/12)^((A22-$C$9)*12)-1)/($C$10/12))*(1+$C$10/12)) | D22: =C22-B22
A23: 10 | B23: =$C$6*(1+$C$7/12)^(A23*12) + $C$4*(((1+$C$7/12)^(A23*12)-1)/($C$7/12))*(1+$C$7/12) | C23: =IF(A23<$C$9, B23, ($C$6*(1+$C$7/12)^($C$9*12) + $C$4*(((1+$C$7/12)^($C$9*12)-1)/($C$7/12))*(1+$C$7/12)) * (1+$C$8) * (1+$C$10/12)^((A23-$C$9)*12) + $C$4*(((1+$C$10/12)^((A23-$C$9)*12)-1)/($C$10/12))*(1+$C$10/12)) | D23: =C23-B23
A24: 11 | B24: =$C$6*(1+$C$7/12)^(A24*12) + $C$4*(((1+$C$7/12)^(A24*12)-1)/($C$7/12))*(1+$C$7/12) | C24: =IF(A24<$C$9, B24, ($C$6*(1+$C$7/12)^($C$9*12) + $C$4*(((1+$C$7/12)^($C$9*12)-1)/($C$7/12))*(1+$C$7/12)) * (1+$C$8) * (1+$C$10/12)^((A24-$C$9)*12) + $C$4*(((1+$C$10/12)^((A24-$C$9)*12)-1)/($C$10/12))*(1+$C$10/12)) | D24: =C24-B24
A25: 12 | B25: =$C$6*(1+$C$7/12)^(A25*12) + $C$4*(((1+$C$7/12)^(A25*12)-1)/($C$7/12))*(1+$C$7/12) | C25: =IF(A25<$C$9, B25, ($C$6*(1+$C$7/12)^($C$9*12) + $C$4*(((1+$C$7/12)^($C$9*12)-1)/($C$7/12))*(1+$C$7/12)) * (1+$C$8) * (1+$C$10/12)^((A25-$C$9)*12) + $C$4*(((1+$C$10/12)^((A25-$C$9)*12)-1)/($C$10/12))*(1+$C$10/12)) | D25: =C25-B25
... A33: 20 | B33: =$C$6*(1+$C$7/12)^(A33*12) + $C$4*(((1+$C$7/12)^(A33*12)-1)/($C$7/12))*(1+$C$7/12) | C33: =IF(A33<$C$9, B33, ($C$6*(1+$C$7/12)^($C$9*12) + $C$4*(((1+$C$7/12)^($C$9*12)-1)/($C$7/12))*(1+$C$7/12)) * (1+$C$8) * (1+$C$10/12)^((A33-$C$9)*12) + $C$4*(((1+$C$10/12)^((A33-$C$9)*12)-1)/($C$10/12))*(1+$C$10/12)) | D33: =C33-B33

Sheet VIP — Plan FIRE avancé
A1: 👑 — Plan d'indépendance financière — multi-taux
A2: Compare plusieurs taux de retrait et intègre l'inflation pour estimer ton capital cible réel.
A4: Dépenses annuelles actuelles (€) | C4: 24000
A5: Inflation annuelle estimée | C5: 0.02
A6: Nombre d'années avant le départ visé | C6: 20
A7: Capital actuel déjà investi (€) | C7: 15000
A8: Versement mensuel actuel (€) | C8: 500
A9: Rendement annuel estimé | C9: 0.06
A12: Dépenses annuelles projetées à la date visée (ajustées de l'inflation) | C12: =C4*(1+C5)^C6
A15: Taux de retrait | B15: Capital cible nécessaire | C15: Capital projeté (versements actuels) | D15: Écart | E15: Objectif atteint ?
A16: 0.03 | B16: =$C$12/A16 | C16: =$C$7*(1+$C$9/12)^($C$6*12) + $C$8*(((1+$C$9/12)^($C$6*12)-1)/($C$9/12))*(1+$C$9/12) | D16: =C16-B16 | E16: =IF(D16>=0,"✅ Oui","❌ Pas encore")
A17: 0.035 | B17: =$C$12/A17 | C17: =$C$7*(1+$C$9/12)^($C$6*12) + $C$8*(((1+$C$9/12)^($C$6*12)-1)/($C$9/12))*(1+$C$9/12) | D17: =C17-B17 | E17: =IF(D17>=0,"✅ Oui","❌ Pas encore")
A18: 0.04 | B18: =$C$12/A18 | C18: =$C$7*(1+$C$9/12)^($C$6*12) + $C$8*(((1+$C$9/12)^($C$6*12)-1)/($C$9/12))*(1+$C$9/12) | D18: =C18-B18 | E18: =IF(D18>=0,"✅ Oui","❌ Pas encore")

Sheet Elite — Véhicules fiscaux BE
A1: 🏆 — Comparateur de véhicules d'épargne belges
A2: Compare 3 grandes familles de véhicules sur 20 ans. Hypothèses éditables — vérifie toujours les seuils et taux en vigueur, ils évoluent chaque année.
A4: Versement mensuel équivalent (€) | C4: 250
A5: Durée (années) | C5: 20
A8: Véhicule | B8: Rendement brut estimé | C8: Frais/taxes annuels estimés | D8: Avantage fiscal à l'entrée | E8: Capital brut estimé (20 ans) | F8: Capital net estimé après frais
A9: Compte-titres (ETF) | B9: 0.06 | C9: 0.0065 | D9: Aucun | E9: =$C$4*(((1+((B9-C9)/12))^($C$5*12)-1)/((B9-C9)/12))*(1+((B9-C9)/12)) | F9: =E9*(1+0)
A10: Assurance épargne (branche 21) | B10: 0.025 | C10: 0.02 | D10: Aucun (hors cas spécifiques) | E10: =$C$4*(((1+((B10-C10)/12))^($C$5*12)-1)/((B10-C10)/12))*(1+((B10-C10)/12)) | F10: =E10*(1+0)
A11: Épargne-pension (3e pilier) | B11: 0.05 | C11: 0.01 | D11: Réduction d'impôt à l'entrée (indicative) | E11: =$C$4*(((1+((B11-C11)/12))^($C$5*12)-1)/((B11-C11)/12))*(1+((B11-C11)/12)) | F11: =E11*(1+0.3)
A14: ⚠️ Modèle très simplifié à but pédagogique : ne tient pas compte de la fiscalité de sortie (ex. taxe sur l'épargne-pension à 60 ans), des plafonds légaux, ni des frais d'entrée. À utiliser comme point de départ de réflexion, pas comme simulation officielle.

Sheet Elite — Plan multi-objectifs
A1: 🏆 — Plan d'épargne multi-objectifs
A2: Renseigne jusqu'à 3 objectifs en parallèle (retraite, achat immobilier, études des enfants…) pour voir le versement mensuel total requis.
A5: Objectif | B5: Montant cible (€) | C5: Horizon (années) | D5: Capital déjà épargné pour cet objectif (€) | E5: Rendement annuel estimé | F5: Versement mensuel requis
A6: Retraite anticipée | B6: 400000 | C6: 25 | D6: 5000 | E6: 0.06 | F6: =MAX(0, (B6 - D6*(1+E6/12)^(C6*12)) / ((((1+E6/12)^(C6*12)-1)/(E6/12))*(1+E6/12)))
A7: Apport achat immobilier | B7: 60000 | C7: 6 | D7: 8000 | E7: 0.03 | F7: =MAX(0, (B7 - D7*(1+E7/12)^(C7*12)) / ((((1+E7/12)^(C7*12)-1)/(E7/12))*(1+E7/12)))
A8: Études des enfants | B8: 30000 | C8: 15 | D8: 0 | E8: 0.04 | F8: =MAX(0, (B8 - D8*(1+E8/12)^(C8*12)) / ((((1+E8/12)^(C8*12)-1)/(E8/12))*(1+E8/12)))
A10: TOTAL versement mensuel requis (tous objectifs) | F10: =SUM(F6:F8)
A13: Astuce : si le total dépasse ta capacité d'épargne réelle, priorise — tous les objectifs n'ont pas besoin de démarrer en même temps.
